{"strategy": 8, "indicators1": {"default": true, "text": "test1 lol", "enabled": false}, "indicators2": {"text": "test2 22", "enabled": true}, "indicators3": {"text": "test3 33", "enabled": true}, "time_from": 1625097600000, "time_until": 1631232000000, "time_from_index": 3, "time_until_index": 2, "time_from_date": false, "time_until_date": false, "time_until_enabled": true, "hyperopt": {"hyperopt": true, "loss_function": 3, "epochs": "30", "search_space_all": true, "search_space_default": false, "search_space_buy": true, "search_space_sell": true, "search_space_roi": false, "search_space_stoploss": false, "search_space_trailing": false, "search_space_protect": false}, "config_default": true, "config_selection": 2, "config": "config.json", "pairs1": "BTC\nETH\nIOTA\nNANO\nENJ\nUNI\n", "pairs2": "22", "pairs3": "333", "plot_pair": 3, "plot_profit": true}